yahoofinancials/__init__.py
yahoofinancials/cache.py
yahoofinancials/calcs.py
yahoofinancials/data.py
yahoofinancials/maps.py
yahoofinancials/sessions.py
yahoofinancials/utils.py
yahoofinancials/yf.py
yahoofinancials-1.20.dist-info/DESCRIPTION.rst
yahoofinancials-1.20.dist-info/METADATA
yahoofinancials-1.20.dist-info/RECORD
yahoofinancials-1.20.dist-info/WHEEL
yahoofinancials-1.20.dist-info/metadata.json
yahoofinancials-1.20.dist-info/top_level.txt
