Metadata-Version: 2.0
Name: yahoofinancials
Version: 1.20
Summary: A powerful financial data module used for pulling both fundamental and technical data from Yahoo Finance
Home-page: https://github.com/JECSand/yahoofinancials
Author: Connor Sanders
Author-email: connor@exceleri.com
License: MIT
Download-URL: https://github.com/JECSand/yahoofinancials/archive/1.20.tar.gz
Keywords: finance data,stocks,commodities,cryptocurrencies,currencies,forex,yahoo finance
Platform: UNKNOWN
Classifier: Development Status :: 5 - Production/Stable
Classifier: Intended Audience :: Developers
Classifier: Intended Audience :: Financial and Insurance Industry
Classifier: Topic :: Office/Business :: Financial :: Investment
Classifier: Topic :: Software Development :: Libraries :: Python Modules
Classifier: Operating System :: OS Independent
Classifier: License :: OSI Approved :: MIT License
Classifier: Programming Language :: Python :: 3.7
Classifier: Programming Language :: Python :: 3.8
Classifier: Programming Language :: Python :: 3.9
Classifier: Programming Language :: Python :: 3.10
Classifier: Programming Language :: Python :: 3.11
Classifier: Programming Language :: Python :: 3.12
Requires-Dist: appdirs (>=1.4.4)
Requires-Dist: beautifulsoup4 (>=4.11.1)
Requires-Dist: frozendict (>=2.3.4)
Requires-Dist: lxml (>=4.9.1)
Requires-Dist: peewee (>=3.16.2)
Requires-Dist: pytz (>=2022.5)
Requires-Dist: requests (>=2.31)
